rattlepy/__init__.py
rattlepy/__main__.py
rattlepy/elements.py
rattlepy/templating.py
rattlepy/utils.py
rattlepy/environment/__init__.py
rattlepy/environment/placeholder.py
rattlepy-0.0.5a1.dist-info/DESCRIPTION.rst
rattlepy-0.0.5a1.dist-info/METADATA
rattlepy-0.0.5a1.dist-info/RECORD
rattlepy-0.0.5a1.dist-info/WHEEL
rattlepy-0.0.5a1.dist-info/metadata.json
rattlepy-0.0.5a1.dist-info/top_level.txt
